project_cli/__init__.py
project_cli/__main__.py
project_cli/templates.py
project_cli-0.1.1.dist-info/METADATA
project_cli-0.1.1.dist-info/RECORD
project_cli-0.1.1.dist-info/WHEEL
project_cli-0.1.1.dist-info/entry_points.txt
project_cli-0.1.1.dist-info/top_level.txt
