Metadata-Version: 2.1
Name: project-cli
Version: 0.1.1
Summary: A commandline interface for creating project structures
Home-page: UNKNOWN
Author: Ramon Hagenaars
Author-email: UNKNOWN
License: UNKNOWN
Platform: UNKNOWN
